deployrecipes.py
deployrecipes-1.0.1.dist-info/DESCRIPTION.rst
deployrecipes-1.0.1.dist-info/METADATA
deployrecipes-1.0.1.dist-info/RECORD
deployrecipes-1.0.1.dist-info/WHEEL
deployrecipes-1.0.1.dist-info/entry_points.txt
deployrecipes-1.0.1.dist-info/metadata.json
deployrecipes-1.0.1.dist-info/top_level.txt
