Metadata-Version: 2.0
Name: deployrecipes
Version: 1.0.1
Summary: Buildout recipes for PasteDeploy
Home-page: http://packages.python.org/deployrecipes/
Author: 2degrees Limited
Author-email: 2degrees-floss@googlegroups.com
License: BSD (http://dev.2degreesnetwork.com/p/2degrees-license.html)
Keywords: buildout recipe wsgi paste deploy web PasteDeploy
Platform: UNKNOWN
Classifier: Development Status :: 5 - Production/Stable
Classifier: Environment :: Web Environment
Classifier: Framework :: Buildout
Classifier: Framework :: Paste
Classifier: Intended Audience :: Developers
Classifier: License :: OSI Approved :: BSD License
Classifier: Natural Language :: English
Classifier: Operating System :: OS Independent
Classifier: Programming Language :: Python :: 2
Classifier: Topic :: Internet :: WWW/HTTP
Classifier: Topic :: Internet :: WWW/HTTP :: WSGI
Requires-Dist: Paste
Requires-Dist: PasteDeploy (>=1.3.3)
Requires-Dist: zc.buildout (>=1.4.0)
Requires-Dist: zc.recipe.egg (>=1.2.2)
